numtxt.py
numtxt-1.3.0.dist-info/LICENSE
numtxt-1.3.0.dist-info/METADATA
numtxt-1.3.0.dist-info/WHEEL
numtxt-1.3.0.dist-info/top_level.txt
numtxt-1.3.0.dist-info/RECORD
