Metadata-Version: 2.1
Name: numtxt
Version: 1.3.0
Summary: gives full and approximate written forms of numbers
Home-page: http://github.com/Electrostatus/numtxt
Author: Philip Herd
License: GPLv3
Keywords: approximation written word number name numeral si prefix cardinal ordinal precedence
Platform: UNKNOWN
Classifier: Operating System :: OS Independent
Classifier: License :: OSI Approved :: GNU General Public License v3 (GPLv3)
Classifier: Development Status :: 5 - Production/Stable
Classifier: Programming Language :: Python :: 2
Classifier: Programming Language :: Python :: 3
Classifier: Natural Language :: English
Classifier: Topic :: Scientific/Engineering :: Mathematics
Classifier: Topic :: Text Processing :: Linguistic
Classifier: Intended Audience :: Education
License-File: LICENSE
